{"metadata": {"dbt_schema_version": "https://schemas.getdbt.com/dbt/run-results/v6.json", "dbt_version": "1.8.0", "generated_at": "2024-05-18T14:05:51.429278Z", "invocation_id": "b9dd0abd-e2fb-442f-ab2d-70f1c9a06bf9", "env": {}}, "results": [{"status": "success", "timing": [{"name": "compile", "started_at": "2024-05-18T14:05:51.412587Z", "completed_at": "2024-05-18T14:05:51.420622Z"}, {"name": "execute", "started_at": "2024-05-18T14:05:51.421121Z", "completed_at": "2024-05-18T14:05:51.421138Z"}], "thread_id": "Thread-1 (worker)", "execution_time": 0.009655952453613281, "adapter_response": {}, "message": null, "failures": null, "unique_id": "model.flight_log.flight_log", "compiled": true, "compiled_code": "with tmp_flight_log as (\n  select\n    *,\n    first_value(altitude) over (partition by timestamp_trunc(timestamp, minute) order by timestamp rows between unbounded preceding and unbounded following) as first_altitude,\n    last_value(altitude) over (partition by timestamp_trunc(timestamp, minute) order by timestamp rows between unbounded preceding and unbounded following) as last_altitude,\n    first_value(timestamp) over (partition by timestamp_trunc(timestamp, minute) order by timestamp rows between unbounded preceding and unbounded following) as first_timestamp,\n    last_value(timestamp) over (partition by timestamp_trunc(timestamp, minute) order by timestamp rows between unbounded preceding and unbounded following) as last_timestamp\n  from\n    `glider-dash`.`data_lake`.`flight_log`\n),\n\ntmp_flight_log_aggregated as (\n  select\n    min(flight_id) as flight_id,\n    min(pilot) as pilot,\n    min(glider_type) as glider_type,\n    min(glider_id) as glider_id,\n    timestamp_trunc(timestamp, minute) as timestamp,\n    avg(latitude) as latitude,\n    avg(longitude) as longitude,\n    avg(altitude) as altitude,\n    min(circling) as circling,\n    min(first_altitude) as first_altitude,\n    min(last_altitude) as last_altitude,\n    min(first_timestamp) as first_timestamp,\n    min(last_timestamp) as last_timestamp\n  from\n    tmp_flight_log\n  group by\n    timestamp\n)\n\nselect\n  flight_id,\n  pilot,\n  glider_type,\n  glider_id,\n  timestamp,\n  latitude,\n  longitude,\n  altitude,\n  circling,\n  (last_altitude - first_altitude) / timestamp_diff(last_timestamp, first_timestamp, second) as climb_rate\nfrom\n  tmp_flight_log_aggregated\nwhere\n  timestamp_diff(last_timestamp, first_timestamp, second) > 0", "relation_name": "`glider-dash`.`data_warehouse`.`flight_log`"}, {"status": "success", "timing": [{"name": "compile", "started_at": "2024-05-18T14:05:51.423822Z", "completed_at": "2024-05-18T14:05:51.426579Z"}, {"name": "execute", "started_at": "2024-05-18T14:05:51.427114Z", "completed_at": "2024-05-18T14:05:51.427123Z"}], "thread_id": "Thread-1 (worker)", "execution_time": 0.004345417022705078, "adapter_response": {}, "message": null, "failures": null, "unique_id": "model.flight_log.flight_log_with_weather_info", "compiled": true, "compiled_code": "select\n  f.flight_id,\n  f.pilot,\n  f.glider_type,\n  f.glider_id,\n  f.timestamp,\n  f.latitude,\n  f.longitude,\n  f.altitude,\n  f.circling,\n  f.climb_rate,\n  a.temperature,\n  a.wind_speed,\n  a.wind_direction,\n  a.daylight_hours,\n  a.humidity,\n  a.rainfall\nfrom\n  `glider-dash`.`data_warehouse`.`flight_log` as f\nleft join\n  `glider-dash`.`data_lake`.`amedas` as a\n  on\n    timestamp_trunc(timestamp_sub(f.timestamp, interval mod(extract(minute from f.timestamp), 10) minute), minute) = a.timestamp", "relation_name": "`glider-dash`.`data_warehouse`.`flight_log_with_weather_info`"}], "elapsed_time": 0.3409755229949951, "args": {"use_colors": true, "log_format_file": "debug", "require_explicit_package_overrides_for_builtin_materializations": true, "send_anonymous_usage_stats": true, "version_check": true, "populate_cache": true, "printer_width": 80, "defer": false, "partial_parse": true, "profiles_dir": "/home/runner/work/glider-data-infrastructure/glider-data-infrastructure/dbt/flight_log", "show_resource_report": false, "log_file_max_bytes": 10485760, "write_json": true, "compile": true, "source_freshness_run_project_hooks": false, "strict_mode": false, "favor_state": false, "log_level_file": "debug", "cache_selected_only": false, "print": true, "macro_debugging": false, "select": [], "static": false, "require_resource_names_without_spaces": false, "project_dir": "/home/runner/work/glider-data-infrastructure/glider-data-infrastructure/dbt/flight_log", "log_path": "/home/runner/work/glider-data-infrastructure/glider-data-infrastructure/dbt/flight_log/logs", "warn_error_options": {"include": [], "exclude": []}, "quiet": false, "vars": {}, "introspect": true, "enable_legacy_logger": false, "log_format": "default", "empty_catalog": false, "log_level": "info", "use_colors_file": true, "partial_parse_file_diff": true, "indirect_selection": "eager", "which": "generate", "static_parser": true, "invocation_command": "dbt docs generate", "exclude": []}}